{
    "url": "https://www.hsbc.com.hk/gpib/channel/proxy/abslSvc/enqBranchABSL",
    "method": "POST",
    "json": true,
    "headers": {
        "content-type": "application/json"
    },
    "body": {
        "countryCode": "HK",
        "locale": "zh-hk",
        "locationTypes": [
            {
                "locationType": "ssb"
            }
        ],
        "services": [
            {
                "service": "show-all-results"
            }
        ],
        "cLat": 22.419461024460098,
        "cLng": 114.1678022327576,
        "bottomLeftLat": 22.397467790332893,
        "bottomLeftLng": 114.13346995736697,
        "topRightLat": 22.4414542585873,
        "topRightLng": 114.20213450814822
    }
},
{
    "responseInfo": {
        "reasons": [],
        "correlationId": null
    },
    "localFields": null,
    "extensions": [],
    "exceedMaximum": false,
    "systemTime": null,
    "results": []
}