{
    "url": "https://www.hsbc.com.hk/gpib/channel/proxy/abslSvc/enqBranchABSL",
    "method": "POST",
    "json": true,
    "headers": {
        "content-type": "application/json"
    },
    "body": {
        "countryCode": "HK",
        "locale": "zh-hk",
        "locationTypes": [
            {
                "locationType": "ssb"
            }
        ],
        "services": [
            {
                "service": "show-all-results"
            }
        ],
        "cLat": 22.3754187481393,
        "cLng": 114.0304731311951,
        "bottomLeftLat": 22.353369705945706,
        "bottomLeftLng": 113.99614085580447,
        "topRightLat": 22.397467790332893,
        "topRightLng": 114.06480540658572
    }
},
{
    "responseInfo": {
        "reasons": [],
        "correlationId": null
    },
    "localFields": null,
    "extensions": [],
    "exceedMaximum": false,
    "systemTime": null,
    "results": [
        {
            "name": "深井理財易中心",
            "locationId": "032-04514",
            "type": "ssb",
            "addInfo": null,
            "facilities": [
                {
                    "facility": "理財易中心"
                }
            ],
            "address": {
                "addrFrmtTyp": null,
                "line1": "新界深井海韻花園地下G6號舖",
                "line2": null,
                "line3": null,
                "city": "荃灣",
                "prov": "新界",
                "postalCde": null,
                "ctryCde": "香港特別行政區",
                "line4": null,
                "lat": "22.36823",
                "lng": "114.06172"
            },
            "workHrs": {
                "lobby": {
                    "monday": "-",
                    "tuesday": "-",
                    "wednesday": "-",
                    "thursday": "-",
                    "friday": "-",
                    "saturday": "-",
                    "sunday": "-"
                },
                "driveThru": {
                    "monday": "00:00 - 23:59",
                    "tuesday": "00:00 - 23:59",
                    "wednesday": "00:00 - 23:59",
                    "thursday": "00:00 - 23:59",
                    "friday": "00:00 - 23:59",
                    "saturday": "00:00 - 23:59",
                    "sunday": "00:00 - 23:59"
                },
                "todayOpenHours": "00:00 - 23:59"
            },
            "services": [
                {
                    "service": "現金提款"
                },
                {
                    "service": "輪椅通道 (自動櫃員機)"
                }
            ],
            "contacts": [
                {
                    "type": null,
                    "name": "電話",
                    "value": "(+852) 2233 3000"
                }
            ],
            "email": null,
            "distance": "3.31 公里"
        }
    ]
}